email_address/__init__.py
email_address/email_address.py
email_address/py.typed
email_address-1.0.0.dist-info/LICENSE
email_address-1.0.0.dist-info/METADATA
email_address-1.0.0.dist-info/WHEEL
email_address-1.0.0.dist-info/top_level.txt
email_address-1.0.0.dist-info/RECORD
